adk_adapter/__init__.py
adk_adapter/adapter.py
adk_adapter/client.py
memory_engine_adapters/__init__.py
memory_engine_adapters/adk_adapter/__init__.py
memory_engine_adapters/adk_adapter/adapter.py
memory_engine_adapters/adk_adapter/adk_example.py
memory_engine_adapters/adk_adapter/client.py
memory_engine_adapters-0.2.0.dist-info/METADATA
memory_engine_adapters-0.2.0.dist-info/WHEEL
memory_engine_adapters-0.2.0.dist-info/top_level.txt
memory_engine_adapters-0.2.0.dist-info/RECORD
