Metadata-Version: 2.4
Name: memory-engine-adapters
Version: 0.2.0
Summary: Adapters that connect Memory Engine to external agent frameworks (e.g., Google ADK).
Author: Memory Engine Team
License: Proprietary
Project-URL: Homepage, https://example.com/memory-engine
Project-URL: Source, https://example.com/memory-engine/adapters
Keywords: memory,adapter,google-adk,llm,agents
Requires-Python: >=3.9
Requires-Dist: httpx<0.29,>=0.27
Provides-Extra: adk
Requires-Dist: google-adk>=0.1.7; extra == "adk"
Provides-Extra: dev
Requires-Dist: pytest>=8.2; extra == "dev"
Requires-Dist: pytest-asyncio>=0.23; extra == "dev"
